xpmtd/__init__.py
xpmtd/metadata.py
xpmtd/spikeglx_metadata_reader.py
xpmtd-0.1.5.dist-info/licenses/LICENSE
xpmtd-0.1.5.dist-info/METADATA
xpmtd-0.1.5.dist-info/WHEEL
xpmtd-0.1.5.dist-info/top_level.txt
xpmtd-0.1.5.dist-info/RECORD
