Metadata-Version: 2.4
Name: xpmtd
Version: 0.1.5
Summary: Handling experimental metadata, mainly paths needed for various pipeline applications
Author-email: Stephen Lenzi <stephen.lenzi@gmail.com>
License: MIT
Project-URL: Homepage, https://github.com/stephenlenzi/xpmtd
Project-URL: Bug Tracker, https://github.com/stephenlenzi/xpmtd/issues
Project-URL: Documentation, https://stephenlenzi.github.io/xpmtd
Project-URL: Source Code, https://github.com/stephenlenzi/xpmtd
Project-URL: User Support, https://github.com/stephenlenzi/xpmtd/issues
Classifier: Development Status :: 2 - Pre-Alpha
Classifier: Programming Language :: Python
Classifier: Programming Language :: Python :: 3
Classifier: Programming Language :: Python :: 3.9
Classifier: Programming Language :: Python :: 3.10
Classifier: Programming Language :: Python :: 3.11
Classifier: Operating System :: OS Independent
Classifier: License :: OSI Approved :: MIT License
Requires-Python: >=3.9.0
License-File: LICENSE
Provides-Extra: dev
Requires-Dist: pytest; extra == "dev"
Requires-Dist: pytest-cov; extra == "dev"
Requires-Dist: coverage; extra == "dev"
Requires-Dist: tox; extra == "dev"
Requires-Dist: mypy; extra == "dev"
Requires-Dist: pre-commit; extra == "dev"
Requires-Dist: ruff; extra == "dev"
Requires-Dist: setuptools_scm; extra == "dev"
Dynamic: license-file
